akit/__init__.py
akit/activation/__init__.py
akit/activation/base.py
akit/activation/console.py
akit/activation/service.py
akit/activation/testrun.py
akit/aspects.py
akit/cli/__init__.py
akit/cli/akitcommand.py
akit/cli/cmdtree/__init__.py
akit/cli/cmdtree/databases/__init__.py
akit/cli/cmdtree/databases/automation.py
akit/cli/cmdtree/generators/__init__.py
akit/cli/cmdtree/generators/upnp.py
akit/cli/cmdtree/landscape.py
akit/cli/cmdtree/network/__init__.py
akit/cli/cmdtree/network/mdns.py
akit/cli/cmdtree/network/upnp.py
akit/cli/cmdtree/servers/__init__.py
akit/cli/cmdtree/servers/results_server.py
akit/cli/cmdtree/testing/__init__.py
akit/cli/cmdtree/testing/constants.py
akit/cli/cmdtree/testing/jobs.py
akit/cli/cmdtree/testing/query.py
akit/cli/cmdtree/testing/run.py
akit/cli/cmdtree/utilities.py
akit/cli/cmdtree/workflow.py
akit/comparisons.py
akit/compat.py
akit/conversions.py
akit/coupling/__init__.py
akit/coupling/basecoupling.py
akit/coupling/coordinatorcoupling.py
akit/coupling/coordinators/sshpoolcoordinatorintegration.py
akit/coupling/coordinators/upnpcoordinatorintegration.py
akit/coupling/coordinators/wirelesscoordinatorintegration.py
akit/coupling/integrationcoupling.py
akit/coupling/sshpoolcoordinatorintegration.py
akit/coupling/upnpcoordinatorintegration.py
akit/coupling/wirelesscoordinatorintegration.py
akit/datum/__init__.py
akit/datum/dbconnection.py
akit/datum/dbio.py
akit/datum/orm.py
akit/environment/__init__.py
akit/environment/configuration.py
akit/environment/context.py
akit/environment/contextpaths.py
akit/environment/optionoverrides.py
akit/environment/system.py
akit/environment/variables.py
akit/exceptions.py
akit/extensible.py
akit/extensionpoints.py
akit/friendlyidentifier.py
akit/interfaces/icommandrunner.py
akit/interfaces/iexcludefilter.py
akit/interfaces/iincludefilter.py
akit/interop/__init__.py
akit/interop/agents/__init__.py
akit/interop/agents/dnsagent.py
akit/interop/agents/poweragents.py
akit/interop/agents/serialagents.py
automationkit-0.5.1.dist-info/WHEEL
automationkit-0.5.1.dist-info/LICENSE.txt
automationkit-0.5.1.dist-info/METADATA
automationkit-0.5.1.dist-info/RECORD
