Metadata-Version: 2.1
Name: automationkit
Version: 0.5.1
Summary: Automation Kit Test Framework
License: LICENSE.txt
Keywords: automation,continuous-integration,distributed-test-framework,distributed-testing-tools,distributed-testing,upnp,test-automation,test-framework,testing,testing-tools
Author: Myron Walker
Author-email: myron.walker@gmail.com
Requires-Python: >=3.8,<4.0
Classifier: License :: OSI Approved :: MIT License
Classifier: License :: Other/Proprietary License
Classifier: Operating System :: POSIX
Classifier: Programming Language :: Python :: 3
Classifier: Programming Language :: Python :: 3.8
Classifier: Programming Language :: Python :: 3.9
Classifier: Programming Language :: Python :: 3.10
Classifier: Programming Language :: Python :: 3.11
Classifier: Programming Language :: Python :: 3
Requires-Dist: click (>=8.1.3,<9.0.0)
Requires-Dist: coverage (>=7.0.4,<8.0.0)
Requires-Dist: debugpy (>=1.6.5,<2.0.0)
Requires-Dist: dlipower (>=1.0.176,<2.0.0)
Requires-Dist: flask (>=2.2.2,<3.0.0)
Requires-Dist: flask-migrate (>=4.0.1,<5.0.0)
Requires-Dist: flask-restx (>=1.0.3,<2.0.0)
Requires-Dist: gunicorn (>=20.1.0,<21.0.0)
Requires-Dist: ipython (>=8.8.0,<9.0.0)
Requires-Dist: netifaces (>=0.11.0,<0.12.0)
Requires-Dist: nmcli (>=1.1.2,<2.0.0)
Requires-Dist: paramiko (>=2.12.0,<3.0.0)
Requires-Dist: pycrunch-trace (>=0.2,<0.3)
Requires-Dist: pylint (>=2.15.9,<3.0.0)
Requires-Dist: pyreadline3 (>=3.4.1,<4.0.0)
Requires-Dist: pyserial (>=3.5,<4.0)
Requires-Dist: pyyaml (>=6.0,<7.0)
Requires-Dist: requests (>=2.28.1,<3.0.0)
Requires-Dist: rich (>=13.0.1,<14.0.0)
Requires-Dist: rope (>=1.6.0,<2.0.0)
Requires-Dist: ssdp (>=1.1.1,<2.0.0)
Requires-Dist: werkzeug (>=2.2.2,<3.0.0)
Requires-Dist: zeroconf (>=0.47.1,<0.48.0)
